grilled/network/__init__.py
grilled_network-0.1.0.dist-info/WHEEL
grilled_network-0.1.0.dist-info/METADATA
grilled_network-0.1.0.dist-info/RECORD
