Metadata-Version: 2.1
Name: grilled-network
Version: 0.1.0
Summary: 
Author: hans
Author-email: dxzenghan@163.com
Requires-Python: >=3.7,<4.0
Classifier: Programming Language :: Python :: 3
Classifier: Programming Language :: Python :: 3.7
Classifier: Programming Language :: Python :: 3.8
Classifier: Programming Language :: Python :: 3.9
Requires-Dist: networkx (>=2.5,<3.0)
